psycopg_toolkit/__init__.py
psycopg_toolkit/exceptions.py
psycopg_toolkit/core/__init__.py
psycopg_toolkit/core/config.py
psycopg_toolkit/core/database.py
psycopg_toolkit/core/factory.py
psycopg_toolkit/core/transaction.py
psycopg_toolkit/repositories/__init__.py
psycopg_toolkit/repositories/base.py
psycopg_toolkit/utils/__init__.py
psycopg_toolkit/utils/json_handler.py
psycopg_toolkit/utils/psychopg_helper.py
psycopg_toolkit/utils/type_inspector.py
psycopg_toolkit-0.2.2.dist-info/METADATA
psycopg_toolkit-0.2.2.dist-info/WHEEL
psycopg_toolkit-0.2.2.dist-info/licenses/LICENSE
psycopg_toolkit-0.2.2.dist-info/RECORD
