Metadata-Version: 2.4
Name: psycopg-toolkit
Version: 0.2.2
Summary: A Python PostgreSQL database utility with connection pooling
Project-URL: Homepage, https://github.com/descoped/psycopg-toolkit
Project-URL: Repository, https://github.com/descoped/psycopg-toolkit
Project-URL: Documentation, https://github.com/descoped/psycopg-toolkit/tree/master/docs
Project-URL: Issues, https://github.com/descoped/psycopg-toolkit/issues
Author-email: Ove Ranheim <oranheim@gmail.com>
License: MIT
License-File: LICENSE
Keywords: async,database,jsonb,pool,postgresql,psycopg,repository-pattern
Classifier: Development Status :: 4 - Beta
Classifier: Framework :: AsyncIO
Classifier: Framework :: Pydantic :: 2
Classifier: Intended Audience :: Developers
Classifier: License :: OSI Approved :: MIT License
Classifier: Operating System :: OS Independent
Classifier: Programming Language :: Python :: 3
Classifier: Programming Language :: Python :: 3.11
Classifier: Programming Language :: Python :: 3.12
Classifier: Programming Language :: Python :: 3.13
Classifier: Topic :: Database
Classifier: Topic :: Database :: Database Engines/Servers
Classifier: Topic :: Software Development :: Libraries :: Python Modules
Classifier: Typing :: Typed
Requires-Python: >=3.11
Requires-Dist: psycopg-pool>=3.2.4
Requires-Dist: psycopg>=3.2.3
Requires-Dist: pydantic>=2.10.5
Requires-Dist: tenacity>=9.0.0
